sprockets.http-2.5.1-py3.10-nspkg.pth
sprockets/http/__init__.py
sprockets/http/app.py
sprockets/http/mixins.py
sprockets/http/runner.py
sprockets/http/testing.py
sprockets.http-2.5.1.dist-info/LICENSE
sprockets.http-2.5.1.dist-info/METADATA
sprockets.http-2.5.1.dist-info/WHEEL
sprockets.http-2.5.1.dist-info/entry_points.txt
sprockets.http-2.5.1.dist-info/namespace_packages.txt
sprockets.http-2.5.1.dist-info/top_level.txt
sprockets.http-2.5.1.dist-info/zip-safe
sprockets.http-2.5.1.dist-info/RECORD
