Metadata-Version: 2.1
Name: sprockets.http
Version: 2.5.1
Summary: Tornado HTTP application runner
Home-page: https://github.com/sprockets/sprockets.http
Author: AWeber Communications
Author-email: api@aweber.com
License: BSD
Classifier: Development Status :: 5 - Production/Stable
Classifier: Environment :: No Input/Output (Daemon)
Classifier: Intended Audience :: Developers
Classifier: License :: OSI Approved :: BSD License
Classifier: Natural Language :: English
Classifier: Operating System :: OS Independent
Classifier: Programming Language :: Python :: 3
Classifier: Programming Language :: Python :: 3.9
Classifier: Programming Language :: Python :: 3.10
Classifier: Programming Language :: Python :: Implementation :: CPython
Classifier: Topic :: Internet :: WWW/HTTP
Classifier: Topic :: Software Development :: Libraries
Classifier: Topic :: Software Development :: Libraries :: Python Modules
Requires-Python: >=3.5
License-File: LICENSE
Requires-Dist: setuptools>=64
Requires-Dist: tornado<7,>=5
Provides-Extra: sentry
Requires-Dist: sentry-sdk<2,>=1.5.4; extra == "sentry"
